McCalc/__init__.py
McCalc/calc_tela.py
McCalc/term_calc.py
McCalc-0.0.10.dist-info/LICENSE
McCalc-0.0.10.dist-info/METADATA
McCalc-0.0.10.dist-info/WHEEL
McCalc-0.0.10.dist-info/top_level.txt
McCalc-0.0.10.dist-info/RECORD
