Metadata-Version: 2.1
Name: McCalc
Version: 0.0.10
Summary: Uma calculadora que funciona no modo com interface e sem interface.
Author-email: Maciel Alves Alves <maciel70455@gmail.com>
Project-URL: Homepage, https://github.com/macielalves/McCalc
Project-URL: BugTracker, https://github.com/macielalves/McCalc/issues
Classifier: Programming Language :: Python :: 3
Classifier: License :: OSI Approved :: MIT License
Classifier: Operating System :: OS Independent
Requires-Python: >=3.7
License-File: LICENSE
